chatgptmax/__init__.py
chatgptmax/clean.py
chatgptmax/read_data.py
chatgptmax/send.py
chatgptmax-2.3.5.dist-info/LICENSE
chatgptmax-2.3.5.dist-info/METADATA
chatgptmax-2.3.5.dist-info/WHEEL
chatgptmax-2.3.5.dist-info/top_level.txt
chatgptmax-2.3.5.dist-info/RECORD
