Metadata-Version: 2.1
Name: chatgptmax
Version: 2.3.5
Summary: Take large input or read a file and send it in chunks to ChatGPT.
Author-email: Victoria Drake <hello@victoria.dev>
Project-URL: Homepage, https://github.com/victoriadrake/chatgptmax/
Project-URL: Bug Tracker, https://github.com/victoriadrake/chatgptmax/issues
Classifier: License :: OSI Approved :: MIT License
Classifier: Operating System :: OS Independent
Classifier: Programming Language :: Python :: 3
Classifier: Topic :: Software Development :: Libraries :: Python Modules
Requires-Python: >=3.7
License-File: LICENSE
